rtl/rv32/rv32_defs.vh
//===================================================================
// rv32_defs.vh — RV32IM instruction-set constants and helper macros
// Verilog-2001, Yosys-synthesizable. Include once.
//===================================================================
`ifndef RV32_DEFS_VH
`define RV32_DEFS_VH

// ---------- opcodes (7-bit [6:0]) ----------
`define OP_LUI      7'b0110111
`define OP_AUIPC    7'b0010111
`define OP_JAL      7'b1101111
`define OP_JALR     7'b1100111
`define OP_BRANCH   7'b1100011
`define OP_LOAD     7'b0000011
`define OP_STORE    7'b0100011
`define OP_OPIMM    7'b0010011
`define OP_OP       7'b0110011
`define OP_MISCMEM  7'b0001111
`define OP_SYSTEM   7'b1110011

// ---------- funct3 (LOAD/STORE sizes) ----------
`define F3_LB 3'b000
`define F3_LH 3'b001
`define F3_LW 3'b010
`define F3_LBU 3'b100
`define F3_LHU 3'b101

`define F3_SB 3'b000
`define F3_SH 3'b001
`define F3_SW 3'b010

// ---------- funct3 (BRANCH) ----------
`define F3_BEQ 3'b000
`define F3_BNE 3'b001
`define F3_BLT 3'b100
`define F3_BGE 3'b101
`define F3_BLTU 3'b110
`define F3_BGEU 3'b111

// ---------- funct3 (OPIMM / OP arith-logic) ----------
`define F3_ADDI 3'b000
`define F3_SLTI 3'b010
`define F3_SLTIU 3'b011
`define F3_XORI 3'b100
`define F3_ORI  3'b110
`define F3_ANDI 3'b111
`define F3_SSHIFT 3'b001   // SLLI
`define F3_RSHIFT 3'b101   // SRLI / SRAI

`define F3_ADDSUB 3'b000
`define F3_SLL  3'b001
`define F3_SLT  3'b010
`define F3_SLTU 3'b011
`define F3_XOR  3'b100
`define F3_SRL  3'b101
`define F3_OR   3'b110
`define F3_AND  3'b111

// ---------- funct3 (M extension) ----------
`define F3_MUL     3'b000
`define F3_MULH    3'b001
`define F3_MULHSU  3'b010
`define F3_MULHU   3'b011
`define F3_DIV     3'b100
`define F3_DIVU    3'b101
`define F3_REM     3'b110
`define F3_REMU    3'b111
`define F7_M        7'b0000001

// ---------- funct3 (CSR) ----------
`define F3_CSRRW  3'b001
`define F3_CSRRS  3'b010
`define F3_CSRRC  3'b011
`define F3_CSRRWI 3'b101
`define F3_CSRRSI 3'b110
`define F3_CSRRCI 3'b111

// ---------- SYSTEM immediate/rs2 encodings ----------
`define SYST_ECALL  12'h000
`define SYST_EBREAK 12'h001
`define SYST_MRET   12'h302
`define SYST_WFI    12'h105

// ---------- CSR addresses (low 12 bits) ----------
`define CSR_MSTATUS 12'h300
`define CSR_MCAUSE  12'h342
`define CSR_MEPC    12'h341
`define CSR_MTVEC   12'h305
`define CSR_MIE     12'h304
`define CSR_MIP     12'h344

// ---------- trap causes ----------
`define CAUSE_ILLEGAL_INSTR    32'd2
`define CAUSE_EBREAK           32'd3
`define CAUSE_ECALL_M          32'd11
`define CAUSE_LOAD_MISALIGN    32'd4
`define CAUSE_STORE_MISALIGN   32'd6
`define CAUSE_TIMER_IRQ        32'h8000_0005  // M.TIMER (trigger); MPP-independent for now

// ---------- MUL/DIV operator codes (core-internal) ----------
`define MOP_NONE   3'b000
`define MOP_MUL    3'b001
`define MOP_MULH   3'b010
`define MOP_MULHSU 3'b011
`define MOP_MULHU  3'b100
`define MOP_DIV    3'b101
`define MOP_DIVU   3'b110
`define MOP_REM    3'b111
`define MOP_REMU   3'b111

`endif

open/designs/riscv_doom_soc/src/rtl/rv32/rv32_muldiv.v
//====================================================================
// rv32_muldiv.v - multicycle M-extension engine (multiply + divide).
// op_i carries the raw funct3 of the M instruction:
//   MUL=000 MULH=001 MULHSU=010 MULHU=011 DIV=100 DIVU=101 REM=110 REMU=111
// Notice this encoding (bit2 == 0) selects multiply vs divide, so REM and
// REMU are naturally distinct here (unlike a sparse 3-bit opcode).
//
// Multiplication : shift-add, 32 iterations (~36 cycles)
// Division       : restoring shift-subtract MSB-first (~36 cycles)
// Sign handling  : magnitude arithmetic + two's-complement adjust
// Spec edge cases:
//   DIV/DIVU by zero  -> quotient 0xFFFFFFFF, remainder = dividend
//   MIN_INT / -1      -> quotient MIN_INT, remainder 0  (from magnitude math)
//
// Interface: start_i pulses once; busy_o high while computing;
// done_o pulses once with res_o final.
//====================================================================
`include "rv32_defs.vh"

module rv32_muldiv (
  input  wire        clk,
  input  wire        rst_n,
  input  wire        start_i,
  input  wire [31:0] a_i,
  input  wire [31:0] b_i,
  input  wire [2:0]  op_i,
  output reg  [31:0] res_o,
  output reg         done_o,
  output reg         busy_o
);

  localparam [1:0] S_IDLE = 2'd0, S_RUN = 2'd1, S_FIN = 2'd2, S_DONE = 2'd3;

  wire is_mul   = ~op_i[2];                      // MUL/MULH/MULHSU/MULHU
  wire a_signed = (op_i==3'b000)||(op_i==3'b001)||(op_i==3'b010)|| // MUL,MULH,MULHSU
                  (op_i==3'b100)||(op_i==3'b110);                  // DIV,REM
  wire b_signed = (op_i==3'b000)||(op_i==3'b001)||
                  (op_i==3'b100)||(op_i==3'b110);                  // DIV,REM
  wire is_rem   = (op_i==3'b110)||(op_i==3'b111);                  // REM,REMU

  wire [31:0] amag = (a_signed && a_i[31]) ? (~a_i + 32'h1) : a_i;
  wire [31:0] bmag = (b_signed && b_i[31]) ? (~b_i + 32'h1) : b_i;
  wire        la   = a_signed && a_i[31];
  wire        lb   = b_signed && b_i[31];

  reg  [1:0]  st;
  reg  [5:0]  step;
  reg  [31:0] ma, mb;                  // operand magnitudes
  reg         la_q, lb_q;              // operand signs (latched)
  reg  [63:0] acc, ash;                // multiply state
  reg  [33:0] r;                       // divide working remainder
  reg  [31:0] d, dv;                   // dividend shifts + divisor
  reg  [31:0] q;                       // divide quotient (magnitude)
  reg         zd;                      // divisor is zero

  // result selection (combinational, evaluated while st==S_FIN)
  wire [63:0] mpro = (la_q ^ lb_q) ? (~acc + 64'h1) : acc;
  wire [31:0] qadj = (la_q ^ lb_q) ? (~q  + 32'h1)  : q;
  wire [31:0] radj = la_q ? (~r[31:0] + 32'h1) : r[31:0];

  always @(posedge clk or negedge rst_n) begin
    if (!rst_n) begin
      st <= S_IDLE; busy_o <= 1'b0; done_o <= 1'b0; res_o <= 32'h0;
      step <= 6'd0;
    end else begin
      done_o <= 1'b0;
      case (st)
        S_IDLE: begin
          if (start_i) begin
            st     <= S_RUN;
            busy_o <= 1'b1;
            step   <= 6'd0;
            ma     <= amag; mb <= bmag;
            la_q   <= la;    lb_q <= lb;
            acc    <= 64'h0; ash <= {32'h0, amag};
            r      <= 34'h0; d   <= amag;
            dv     <= bmag;
            q      <= 32'h0;
            zd     <= (bmag == 32'h0);
          end
        end
        S_RUN: begin
          if (is_mul) begin
            if (step == 6'd32) begin
              st <= S_FIN;
            end else begin
              if (mb[step]) acc <= acc + ash;
              ash  <= ash << 1;
              step <= step + 1;
            end
          end else if (zd) begin
            st <= S_FIN;                 // spec result in S_FIN
          end else if (step == 6'd32) begin
            st <= S_FIN;
          end else begin
            if ({r[32:0], d[31]} >= {2'b00, dv}) begin
              r        <= {r[32:0], d[31]} - {2'b00, dv};
              q[31-step] <= 1'b1;
            end else begin
              r <= {r[32:0], d[31]};
            end
            d    <= d << 1;
            step <= step + 1;
          end
        end
        S_FIN: begin
          if (is_mul) begin
            res_o <= (op_i == 3'b000) ? mpro[31:0] : mpro[63:32];
          end else if (zd) begin
            res_o <= is_rem ? a_i : 32'hFFFF_FFFF;   // div-by-zero
          end else begin
            res_o <= is_rem ? radj : qadj;
          end
          st     <= S_DONE;
          busy_o <= 1'b0;
        end
        S_DONE: begin
          done_o <= 1'b1;
          st     <= S_IDLE;
        end
        default: st <= S_IDLE;
      endcase
    end
  end

endmodule

tb/tb_muldiv.v
`timescale 1ns/1ps
`include "rv32_defs.vh"
module tb_muldiv;

  reg clk = 0, rst_n = 0;
  always #5 clk = ~clk;

  reg        start;
  reg  [31:0] a, b;
  reg  [2:0]  op;                    // funct3
  wire [31:0] res;
  wire        done, busy;

  rv32_muldiv uut (.clk(clk), .rst_n(rst_n), .start_i(start),
                   .a_i(a), .b_i(b), .op_i(op),
                   .res_o(res), .done_o(done), .busy_o(busy));

  integer errs = 0;
  reg [31:0] res_q;

  task run;
    begin : rb
      integer k;
      start = 1;
      #11;                 // hold >1 clock, so the engine samples it cleanly
      start = 0;
      for (k = 0; k < 200; k = k + 1) begin
        if (uut.done_o === 1'b1) begin
          #1;                    // res_o settles at the S_FIN->S_DONE edge
          res_q = uut.res_o;
          disable rb;
        end
        @(posedge clk);
      end
      $display("TIMEOUT st=%0d step=%0d", uut.st, uut.step);
      errs = errs + 1; res_q = 32'hEEEEEEEE;
    end
  endtask

  task chk(input [7:0] name, input [31:0] exp);
    begin
      if (res_q === exp) $display("PASS %s", name);
      else begin
        errs = errs + 1;
        $display("FAIL %s got=0x%08X exp=0x%08X", name, res_q, exp);
      end
    end
  endtask

  initial begin
    $dumpfile("muldiv.vcd");
    $dumpvars(0, tb_muldiv);
    #20 rst_n = 1;

    // multiply
    a = 32'h12345678; b = 32'h9abcdef0;
    op = 3'b000; run; chk("mul  ", 32'h242D2080);   // MUL
    op = 3'b011; run; chk("mulhu", 32'h0B00EA4E);   // MULHU
    op = 3'b001; run; chk("mulh ", 32'hF8CC93D6);   // MULH

    a = 32'hC0000000; b = 32'h80000000;
    op = 3'b011; run; chk("muhu2", 32'h60000000);   // MULHU
    op = 3'b001; run; chk("muh_2", 32'h20000000);   // MULH
    op = 3'b010; run; chk("mhsu2", 32'hE0000000);   // MULHSU

    // divide / remainder
    a = 32'hABCD1234; b = 32'h1234;
    op = 3'b101; run; chk("divu ", 32'h00097020);   // DIVU
    op = 3'b111; run; chk("remu ", 32'h00000BB4);   // REMU

    a = 100; b = 7;
    op = 3'b100; run; chk("div  ", 32'd14);          // DIV
    op = 3'b110; run; chk("rem  ", 32'd2);           // REM
    a = -100; b = 7;
    op = 3'b100; run; chk("divn ", 32'hFFFFFFF2);   // -14
    op = 3'b110; run; chk("remn ", 32'hFFFFFFFE);   // -2

    // div-by-zero + MIN/-1 overflow
    a = 42; b = 0;
    op = 3'b100; run; chk("div0 ", 32'hFFFFFFFF);
    op = 3'b110; run; chk("rem0 ", 32'd42);
    op = 3'b101; run; chk("divu0", 32'hFFFFFFFF);
    op = 3'b111; run; chk("remu0", 32'd42);

    a = 32'h80000000; b = 32'hFFFFFFFF;
    op = 3'b100; run; chk("min1 ", 32'h80000000);
    op = 3'b110; run; chk("minr ", 32'h0);

    $display("============================================");
    if (errs == 0) $display("MULDIV UNIT TEST: PASS");
    else           $display("MULDIV UNIT TEST: FAIL (%0d)", errs);
    $finish;
  end

endmodule

muldiv.vcd
$date
	Tue Aug 18 03:09:03 2026
$end
$version
	Icarus Verilog
$end
$timescale
	1ps
$end
$scope module tb_muldiv $end
$var wire 32 ! res [31:0] $end
$var wire 1 " done $end
$var wire 1 # busy $end
$var reg 32 $ a [31:0] $end
$var reg 32 % b [31:0] $end
$var reg 1 & clk $end
$var reg 3 ' op [2:0] $end
$var reg 32 ( res_q [31:0] $end
$var reg 1 ) rst_n $end
$var reg 1 * start $end
$var integer 32 + errs [31:0] $end
$scope module uut $end
$var wire 32 , a_i [31:0] $end
$var wire 1 - a_signed $end
$var wire 32 . b_i [31:0] $end
$var wire 1 / b_signed $end
$var wire 1 & clk $end
$var wire 1 0 is_mul $end
$var wire 1 1 is_rem $end
$var wire 1 2 la $end
$var wire 1 3 lb $end
$var wire 3 4 op_i [2:0] $end
$var wire 1 ) rst_n $end
$var wire 1 * start_i $end
$var wire 32 5 radj [31:0] $end
$var wire 32 6 qadj [31:0] $end
$var wire 64 7 mpro [63:0] $end
$var wire 32 8 bmag [31:0] $end
$var wire 32 9 amag [31:0] $end
$var parameter 2 : S_DONE $end
$var parameter 2 ; S_FIN $end
$var parameter 2 < S_IDLE $end
$var parameter 2 = S_RUN $end
$var reg 64 > acc [63:0] $end
$var reg 64 ? ash [63:0] $end
$var reg 1 # busy_o $end
$var reg 32 @ d [31:0] $end
$var reg 1 " done_o $end
$var reg 32 A dv [31:0] $end
$var reg 1 B la_q $end
$var reg 1 C lb_q $end
$var reg 32 D ma [31:0] $end
$var reg 32 E mb [31:0] $end
$var reg 32 F q [31:0] $end
$var reg 34 G r [33:0] $end
$var reg 32 H res_o [31:0] $end
$var reg 2 I st [1:0] $end
$var reg 6 J step [5:0] $end
$var reg 1 K zd $end
$upscope $end
$scope task chk $end
$var reg 32 L exp [31:0] $end
$var reg 8 M name [7:0] $end
$upscope $end
$scope task run $end
$scope begin rb $end
$var integer 32 N k [31:0] $end
$upscope $end
$upscope $end
$upscope $end
$enddefinitions $end
$comment Show the parameter values. $end
$dumpall
b1 =
b0 <
b10 ;
b11 :
$end
#0
$dumpvars
bx N
bx M
bx L
xK
b0 J
b0 I
b0 H
bx G
bx F
bx E
bx D
xC
xB
bx A
bx @
bx ?
bx >
bx 9
bx 8
bx 7
bx 6
bx 5
bx 4
x3
x2
x1
x0
x/
bx .
x-
bx ,
b0 +
x*
0)
bx (
bx '
0&
bx %
bx $
0#
0"
b0 !
$end
#5000
1&
#10000
0&
#15000
1&
#20000
1-
13
1/
10
b1100101010000110010000100010000 8
b10010001101000101011001111000 9
02
01
0&
1*
b0 '
b0 4
b10011010101111001101111011110000 %
b10011010101111001101111011110000 .
b10010001101000101011001111000 $
b10010001101000101011001111000 ,
1)
#25000
b0 5
b0 6
b0 7
0K
b0 F
b1100101010000110010000100010000 A
b10010001101000101011001111000 @
b0 G
b10010001101000101011001111000 ?
b0 >
1C
0B
b1100101010000110010000100010000 E
b10010001101000101011001111000 D
1#
b1 I
1&
#30000
0&
#31000
b0 N
0*
#35000
b1 J
b100100011010001010110011110000 ?
b1 N
1&
#40000
0&
#45000
b10 J
b1001000110100010101100111100000 ?
b10 N
1&
#50000
0&
#55000
b11 J
b10010001101000101011001111000000 ?
b11 N
1&
#60000
0&
#65000
b100 J
b100100011010001010110011110000000 ?
b100 N
1&
#70000
0&
#75000
b1111111111111111111111111111111011011100101110101001100010000000 7
b101 J
b1001000110100010101100111100000000 ?
b100100011010001010110011110000000 >
b101 N
1&
#80000
0&
#85000
b110 J
b10010001101000101011001111000000000 ?
b110 N
1&
#90000
0&
#95000
b111 J
b100100011010001010110011110000000000 ?
b111 N
1&
#100000
0&
#105000
b1000 J
b1001000110100010101100111100000000000 ?
b1000 N
1&
#110000
0&
#115000
b1111111111111111111111111110110010101000011001000010000010000000 7
b1001 J
b10010001101000101011001111000000000000 ?
b1001101010111100110111101111110000000 >
b1001 N
1&
#120000
0&
#125000
b1010 J
b100100011010001010110011110000000000000 ?
b1010 N
1&
#130000
0&
#135000
b1011 J
b1001000110100010101100111100000000000000 ?
b1011 N
1&
#140000
0&
#145000
b1100 J
b10010001101000101011001111000000000000000 ?
b1100 N
1&
#150000
0&
#155000
b1101 J
b100100011010001010110011110000000000000000 ?
b1101 N
1&
#160000
0&
#165000
b1111111111111111111111011010011000011101100101010010000010000000 7
b1110 J
b1001000110100010101100111100000000000000000 ?
b100101100111100010011010101101111110000000 >
b1110 N
1&
#170000
0&
#175000
b1111 J
b10010001101000101011001111000000000000000000 ?
b1111 N
1&
#180000
0&
#185000
b10000 J
b100100011010001010110011110000000000000000000 ?
b10000 N
1&
#190000
0&
#195000
b1111111111111111111010110111000111000111000111010010000010000000 7
b10001 J
b1001000110100010101100111100000000000000000000 ?
b101001000111000111000111000101101111110000000 >
b10001 N
1&
#200000
0&
#205000
b1111111111111111110001110000100100011010001011010010000010000000 7
b10010 J
b10010001101000101011001111000000000000000000000 ?
b1110001111011011100101110100101101111110000000 >
b10010 N
1&
#210000
0&
#215000
b10011 J
b100100011010001010110011110000000000000000000000 ?
b10011 N
1&
#220000
0&
#225000
b10100 J
b1001000110100010101100111100000000000000000000000 ?
b10100 N
1&
#230000
0&
#235000
b10101 J
b10010001101000101011001111000000000000000000000000 ?
b10101 N
1&
#240000
0&
#245000
b10110 J
b100100011010001010110011110000000000000000000000000 ?
b10110 N
1&
#250000
0&
#255000
b1111111111111011001110011111001101111100001011010010000010000000 7
b10111 J
b1001000110100010101100111100000000000000000000000000 ?
b100110001100000110010000011110100101101111110000000 >
b10111 N
1&
#260000
0&
#265000
b11000 J
b10010001101000101011001111000000000000000000000000000 ?
b11000 N
1&
#270000
0&
#275000
b1111111111101001000001011001110100000100001011010010000010000000 7
b11001 J
b100100011010001010110011110000000000000000000000000000 ?
b10110111110100110001011111011110100101101111110000000 >
b11001 N
1&
#280000
0&
#285000
b11010 J
b1001000110100010101100111100000000000000000000000000000 ?
b11010 N
1&
#290000
0&
#295000
b1111111110100000001101000100001100100100001011010010000010000000 7
b11011 J
b10010001101000101011001111000000000000000000000000000000 ?
b1011111110010111011110011011011110100101101111110000000 >
b11011 N
1&
#300000
0&
#305000
b11100 J
b100100011010001010110011110000000000000000000000000000000 ?
b11100 N
1&
#310000
0&
#315000
b11101 J
b1001000110100010101100111100000000000000000000000000000000 ?
b11101 N
1&
#320000
0&
#325000
b1111110101011001101010010111010000100100001011010010000010000000 7
b11110 J
b10010001101000101011001111000000000000000000000000000000000 ?
b1010100110010101101000101111011011110100101101111110000000 >
b11110 N
1&
#330000
0&
#335000
b1111100011001100100100111101011000100100001011010010000010000000 7
b11111 J
b100100011010001010110011110000000000000000000000000000000000 ?
b11100110011011011000010100111011011110100101101111110000000 >
b11111 N
1&
#340000
0&
#345000
b100000 J
b1001000110100010101100111100000000000000000000000000000000000 ?
b100000 N
1&
#350000
0&
#355000
b10 I
b100001 N
1&
#360000
0&
#365000
0#
b11 I
b100100001011010010000010000000 !
b100100001011010010000010000000 H
b100010 N
1&
#370000
0&
#375000
b0 I
1"
b100011 N
1&
#380000
0&
#385000
0"
b100100 N
1&
#386000
b10011010101111001101111011110000 8
0-
03
0/
1*
b11 '
b11 4
b100100001011010010000010000000 L
b100000 M
b100100001011010010000010000000 (
#390000
0&
#395000
b0 7
b10011010101111001101111011110000 A
b10010001101000101011001111000 ?
b0 >
0C
b10011010101111001101111011110000 E
b0 J
1#
b1 I
1&
#397000
b0 N
0*
#400000
0&
#405000
b1 J
b100100011010001010110011110000 ?
b1 N
1&
#410000
0&
#415000
b10 J
b1001000110100010101100111100000 ?
b10 N
1&
#420000
0&
#425000
b11 J
b10010001101000101011001111000000 ?
b11 N
1&
#430000
0&
#435000
b100 J
b100100011010001010110011110000000 ?
b100 N
1&
#440000
0&
#445000
b100100011010001010110011110000000 7
b101 J
b1001000110100010101100111100000000 ?
b100100011010001010110011110000000 >
b101 N
1&
#450000
0&
#455000
b1101101001110100000011011010000000 7
b110 J
b10010001101000101011001111000000000 ?
b1101101001110100000011011010000000 >
b110 N
1&
#460000
0&
#465000
b11111110110111001011101010010000000 7
b111 J
b100100011010001010110011110000000000 ?
b11111110110111001011101010010000000 >
b111 N
1&
#470000
0&
#475000
b1000100010001000100010001000010000000 7
b1000 J
b1001000110100010101100111100000000000 ?
b1000100010001000100010001000010000000 >
b1000 N
1&
#480000
0&
#485000
b1001 J
b10010001101000101011001111000000000000 ?
b1001 N
1&
#490000
0&
#495000
b11010101111001101111100000000010000000 7
b1010 J
b100100011010001010110011110000000000000 ?
b11010101111001101111100000000010000000 >
b1010 N
1&
#500000
0&
#505000
b111111001001011000101111110000010000000 7
b1011 J
b1001000110100010101100111100000000000000 ?
b111111001001011000101111110000010000000 >
b1011 N
1&
#510000
0&
#515000
b10000111111101101110010111010000010000000 7
b1100 J
b10010001101000101011001111000000000000000 ?
b10000111111101101110010111010000010000000 >
b1100 N
1&
#520000
0&
#525000
b100011001100110011001100110010000010000000 7
b1101 J
b100100011010001010110011110000000000000000 ?
b100011001100110011001100110010000010000000 >
b1101 N
1&
#530000
0&
#535000
b1110 J
b1001000110100010101100111100000000000000000 ?
b1110 N
1&
#540000
0&
#545000
b1101100000001001000110100010010000010000000 7
b1111 J
b10010001101000101011001111000000000000000000 ?
b1101100000001001000110100010010000010000000 >
b1111 N
1&
#550000
0&
#555000
b11111101101001110100000011010010000010000000 7
b10000 J
b100100011010001010110011110000000000000000000 ?
b11111101101001110100000011010010000010000000 >
b10000 N
1&
#560000
0&
#565000
b10001 J
b1001000110100010101100111100000000000000000000 ?
b10001 N
1&
#570000
0&
#575000
b10010 J
b10010001101000101011001111000000000000000000000 ?
b10010 N
1&
#580000
0&
#585000
b10110001010101111001101111011010010000010000000 7
b10011 J
b100100011010001010110011110000000000000000000000 ?
b10110001010101111001101111011010010000010000000 >
b10011 N
1&
#590000
0&
#595000
b111010100100111010000001101011010010000010000000 7
b10100 J
b1001000110100010101100111100000000000000000000000 ?
b111010100100111010000001101011010010000010000000 >
b10100 N
1&
#600000
0&
#605000
b10000011011001001111101001001011010010000010000000 7
b10101 J
b10010001101000101011001111000000000000000000000000 ?
b10000011011001001111101001001011010010000010000000 >
b10101 N
1&
#610000
0&
#615000
b100010101000001111010111000001011010010000010000000 7
b10110 J
b100100011010001010110011110000000000000000000000000 ?
b100010101000001111010111000001011010010000010000000 >
b10110 N
1&
#620000
0&
#625000
b10111 J
b1001000110100010101100111100000000000000000000000000 ?
b10111 N
1&
#630000
0&
#635000
b1101011011100100100111110100001011010010000010000000 7
b11000 J
b10010001101000101011001111000000000000000000000000000 ?
b1101011011100100100111110100001011010010000010000000 >
b11000 N
1&
#640000
0&
#645000
b11001 J
b100100011010001010110011110000000000000000000000000000 ?
b11001 N
1&
#650000
0&
#655000
b110001110101101111011011100100001011010010000010000000 7
b11010 J
b1001000110100010101100111100000000000000000000000000000 ?
b110001110101101111011011100100001011010010000010000000 >
b11010 N
1&
#660000
0&
#665000
b11011 J
b10010001101000101011001111000000000000000000000000000000 ?
b11011 N
1&
#670000
0&
#675000
b11000011011110011010101010100100001011010010000010000000 7
b11100 J
b100100011010001010110011110000000000000000000000000000000 ?
b11000011011110011010101010100100001011010010000010000000 >
b11100 N
1&
#680000
0&
#685000
b111100110101111110001001000100100001011010010000010000000 7
b11101 J
b1001000110100010101100111100000000000000000000000000000000 ?
b111100110101111110001001000100100001011010010000010000000 >
b11101 N
1&
#690000
0&
#695000
b11110 J
b10010001101000101011001111000000000000000000000000000000000 ?
b11110 N
1&
#700000
0&
#705000
b11111 J
b100100011010001010110011110000000000000000000000000000000000 ?
b11111 N
1&
#710000
0&
#715000
b101100000000111010100100111000100100001011010010000010000000 7
b100000 J
b1001000110100010101100111100000000000000000000000000000000000 ?
b101100000000111010100100111000100100001011010010000010000000 >
b100000 N
1&
#720000
0&
#725000
b10 I
b100001 N
1&
#730000
0&
#735000
0#
b11 I
b1011000000001110101001001110 !
b1011000000001110101001001110 H
b100010 N
1&
#740000
0&
#745000
b0 I
1"
b100011 N
1&
#750000
0&
#755000
0"
b100100 N
1&
#756000
b1100101010000110010000100010000 8
1-
13
1/
1*
b1 '
b1 4
b1011000000001110101001001110 L
b1110101 M
b1011000000001110101001001110 (
#760000
0&
#765000
b0 7
b1100101010000110010000100010000 A
b10010001101000101011001111000 ?
b0 >
1C
b1100101010000110010000100010000 E
b0 J
1#
b1 I
1&
#767000
b0 N
0*
#770000
0&
#775000
b1 J
b100100011010001010110011110000 ?
b1 N
1&
#780000
0&
#785000
b10 J
b1001000110100010101100111100000 ?
b10 N
1&
#790000
0&
#795000
b11 J
b10010001101000101011001111000000 ?
b11 N
1&
#800000
0&
#805000
b100 J
b100100011010001010110011110000000 ?
b100 N
1&
#810000
0&
#815000
b1111111111111111111111111111111011011100101110101001100010000000 7
b101 J
b1001000110100010101100111100000000 ?
b100100011010001010110011110000000 >
b101 N
1&
#820000
0&
#825000
b110 J
b10010001101000101011001111000000000 ?
b110 N
1&
#830000
0&
#835000
b111 J
b100100011010001010110011110000000000 ?
b111 N
1&
#840000
0&
#845000
b1000 J
b1001000110100010101100111100000000000 ?
b1000 N
1&
#850000
0&
#855000
b1111111111111111111111111110110010101000011001000010000010000000 7
b1001 J
b10010001101000101011001111000000000000 ?
b1001101010111100110111101111110000000 >
b1001 N
1&
#860000
0&
#865000
b1010 J
b100100011010001010110011110000000000000 ?
b1010 N
1&
#870000
0&
#875000
b1011 J
b1001000110100010101100111100000000000000 ?
b1011 N
1&
#880000
0&
#885000
b1100 J
b10010001101000101011001111000000000000000 ?
b1100 N
1&
#890000
0&
#895000
b1101 J
b100100011010001010110011110000000000000000 ?
b1101 N
1&
#900000
0&
#905000
b1111111111111111111111011010011000011101100101010010000010000000 7
b1110 J
b1001000110100010101100111100000000000000000 ?
b100101100111100010011010101101111110000000 >
b1110 N
1&
#910000
0&
#915000
b1111 J
b10010001101000101011001111000000000000000000 ?
b1111 N
1&
#920000
0&
#925000
b10000 J
b100100011010001010110011110000000000000000000 ?
b10000 N
1&
#930000
0&
#935000
b1111111111111111111010110111000111000111000111010010000010000000 7
b10001 J
b1001000110100010101100111100000000000000000000 ?
b101001000111000111000111000101101111110000000 >
b10001 N
1&
#940000
0&
#945000
b1111111111111111110001110000100100011010001011010010000010000000 7
b10010 J
b10010001101000101011001111000000000000000000000 ?
b1110001111011011100101110100101101111110000000 >
b10010 N
1&
#950000
0&
#955000
b10011 J
b100100011010001010110011110000000000000000000000 ?
b10011 N
1&
#960000
0&
#965000
b10100 J
b1001000110100010101100111100000000000000000000000 ?
b10100 N
1&
#970000
0&
#975000
b10101 J
b10010001101000101011001111000000000000000000000000 ?
b10101 N
1&
#980000
0&
#985000
b10110 J
b100100011010001010110011110000000000000000000000000 ?
b10110 N
1&
#990000
0&
#995000
b1111111111111011001110011111001101111100001011010010000010000000 7
b10111 J
b1001000110100010101100111100000000000000000000000000 ?
b100110001100000110010000011110100101101111110000000 >
b10111 N
1&
#1000000
0&
#1005000
b11000 J
b10010001101000101011001111000000000000000000000000000 ?
b11000 N
1&
#1010000
0&
#1015000
b1111111111101001000001011001110100000100001011010010000010000000 7
b11001 J
b100100011010001010110011110000000000000000000000000000 ?
b10110111110100110001011111011110100101101111110000000 >
b11001 N
1&
#1020000
0&
#1025000
b11010 J
b1001000110100010101100111100000000000000000000000000000 ?
b11010 N
1&
#1030000
0&
#1035000
b1111111110100000001101000100001100100100001011010010000010000000 7
b11011 J
b10010001101000101011001111000000000000000000000000000000 ?
b1011111110010111011110011011011110100101101111110000000 >
b11011 N
1&
#1040000
0&
#1045000
b11100 J
b100100011010001010110011110000000000000000000000000000000 ?
b11100 N
1&
#1050000
0&
#1055000
b11101 J
b1001000110100010101100111100000000000000000000000000000000 ?
b11101 N
1&
#1060000
0&
#1065000
b1111110101011001101010010111010000100100001011010010000010000000 7
b11110 J
b10010001101000101011001111000000000000000000000000000000000 ?
b1010100110010101101000101111011011110100101101111110000000 >
b11110 N
1&
#1070000
0&
#1075000
b1111100011001100100100111101011000100100001011010010000010000000 7
b11111 J
b100100011010001010110011110000000000000000000000000000000000 ?
b11100110011011011000010100111011011110100101101111110000000 >
b11111 N
1&
#1080000
0&
#1085000
b100000 J
b1001000110100010101100111100000000000000000000000000000000000 ?
b100000 N
1&
#1090000
0&
#1095000
b10 I
b100001 N
1&
#1100000
0&
#1105000
0#
b11 I
b11111000110011001001001111010110 !
b11111000110011001001001111010110 H
b100010 N
1&
#1110000
0&
#1115000
b0 I
1"
b100011 N
1&
#1120000
0&
#1125000
0"
b100100 N
1&
#1126000
0-
03
0/
b10000000000000000000000000000000 8
02
b11000000000000000000000000000000 9
1*
b11 '
b11 4
b10000000000000000000000000000000 %
b10000000000000000000000000000000 .
b11000000000000000000000000000000 $
b11000000000000000000000000000000 ,
b11111000110011001001001111010110 L
b100000 M
b11111000110011001001001111010110 (
#1130000
0&
#1135000
b0 7
b10000000000000000000000000000000 A
b11000000000000000000000000000000 @
b11000000000000000000000000000000 ?
b0 >
0C
b10000000000000000000000000000000 E
b11000000000000000000000000000000 D
b0 J
1#
b1 I
1&
#1137000
b0 N
0*
#1140000
0&
#1145000
b1 J
b110000000000000000000000000000000 ?
b1 N
1&
#1150000
0&
#1155000
b10 J
b1100000000000000000000000000000000 ?
b10 N
1&
#1160000
0&
#1165000
b11 J
b11000000000000000000000000000000000 ?
b11 N
1&
#1170000
0&
#1175000
b100 J
b110000000000000000000000000000000000 ?
b100 N
1&
#1180000
0&
#1185000
b101 J
b1100000000000000000000000000000000000 ?
b101 N
1&
#1190000
0&
#1195000
b110 J
b11000000000000000000000000000000000000 ?
b110 N
1&
#1200000
0&
#1205000
b111 J
b110000000000000000000000000000000000000 ?
b111 N
1&
#1210000
0&
#1215000
b1000 J
b1100000000000000000000000000000000000000 ?
b1000 N
1&
#1220000
0&
#1225000
b1001 J
b11000000000000000000000000000000000000000 ?
b1001 N
1&
#1230000
0&
#1235000
b1010 J
b110000000000000000000000000000000000000000 ?
b1010 N
1&
#1240000
0&
#1245000
b1011 J
b1100000000000000000000000000000000000000000 ?
b1011 N
1&
#1250000
0&
#1255000
b1100 J
b11000000000000000000000000000000000000000000 ?
b1100 N
1&
#1260000
0&
#1265000
b1101 J
b110000000000000000000000000000000000000000000 ?
b1101 N
1&
#1270000
0&
#1275000
b1110 J
b1100000000000000000000000000000000000000000000 ?
b1110 N
1&
#1280000
0&
#1285000
b1111 J
b11000000000000000000000000000000000000000000000 ?
b1111 N
1&
#1290000
0&
#1295000
b10000 J
b110000000000000000000000000000000000000000000000 ?
b10000 N
1&
#1300000
0&
#1305000
b10001 J
b1100000000000000000000000000000000000000000000000 ?
b10001 N
1&
#1310000
0&
#1315000
b10010 J
b11000000000000000000000000000000000000000000000000 ?
b10010 N
1&
#1320000
0&
#1325000
b10011 J
b110000000000000000000000000000000000000000000000000 ?
b10011 N
1&
#1330000
0&
#1335000
b10100 J
b1100000000000000000000000000000000000000000000000000 ?
b10100 N
1&
#1340000
0&
#1345000
b10101 J
b11000000000000000000000000000000000000000000000000000 ?
b10101 N
1&
#1350000
0&
